corefgraph/__init__.py
corefgraph/constants.py
corefgraph/text_processor.py
corefgraph/graph/__init__.py
corefgraph/graph/builder.py
corefgraph/graph/nafbuilder.py
corefgraph/graph/wrapper.py
corefgraph/multisieve/__init__.py
corefgraph/multisieve/core.py
corefgraph/multisieve/extractor.py
corefgraph/multisieve/catchers/ConstituentCatcher.py
corefgraph/multisieve/catchers/EnumerableCatcher.py
corefgraph/multisieve/catchers/GoldCatcher.py
corefgraph/multisieve/catchers/NamedEntitiesCatcher.py
corefgraph/multisieve/catchers/PronounCatcher.py
corefgraph/multisieve/catchers/TrainCatcher.py
corefgraph/multisieve/catchers/__init__.py
corefgraph/multisieve/catchers/baseCatcher.py
corefgraph/multisieve/features/NamedEntityTypeannotator.py
corefgraph/multisieve/features/__init__.py
corefgraph/multisieve/features/animacyannotator.py
corefgraph/multisieve/features/baseannotator.py
corefgraph/multisieve/features/constants.py
corefgraph/multisieve/features/constructionannotator.py
corefgraph/multisieve/features/demonymannotator.py
corefgraph/multisieve/features/dependencyannotator.py
corefgraph/multisieve/features/ellipticannotator.py
corefgraph/multisieve/features/genderannotator.py
corefgraph/multisieve/features/genericsannotator.py
corefgraph/multisieve/features/goldannotator.py
corefgraph/multisieve/features/mentiontypeannotator.py
corefgraph/multisieve/features/multiwordannotator.py
corefgraph/multisieve/features/numberannotator.py
corefgraph/multisieve/features/personannotator.py
corefgraph/multisieve/features/speakerannotator.py
corefgraph/multisieve/filters/__init__.py
corefgraph/multisieve/filters/bareNPFilter.py
corefgraph/multisieve/filters/basefilter.py
corefgraph/multisieve/filters/demonymFilter.py
corefgraph/multisieve/filters/interjectionFilter.py
corefgraph/multisieve/filters/invalidWordFilter.py
corefgraph/multisieve/filters/nonwordFilter.py
corefgraph/multisieve/filters/partitiveFilter.py
corefgraph-1.2.3.dist-info/DESCRIPTION.rst
corefgraph-1.2.3.dist-info/METADATA
corefgraph-1.2.3.dist-info/RECORD
corefgraph-1.2.3.dist-info/WHEEL
corefgraph-1.2.3.dist-info/entry_points.txt
corefgraph-1.2.3.dist-info/metadata.json
corefgraph-1.2.3.dist-info/top_level.txt
