Metadata-Version: 2.0
Name: corefgraph
Version: 1.2.3
Summary: Module to resolve intra-document coreference.
Home-page: https://bitbucket.org/josu/corefgraph/
Author: Josu Bermudez, Rodrigo Agerri
Author-email: josu.bermudez@deusto.es, rodrigo.agerri@ehu.es
License: Apache License Version 2.0
Download-URL: https://bitbucket.org/Josu/corefgraph//get/default.tar.gz
Platform: UNKNOWN
Classifier: Programming Language :: Python
Classifier: Programming Language :: Python :: 2.7
Classifier: Development Status :: 4 - Beta
Classifier: Environment :: Other Environment
Classifier: Intended Audience :: Science/Research
Classifier: Intended Audience :: Developers
Classifier: License :: OSI Approved :: Apache Software License
Classifier: Operating System :: OS Independent
Classifier: Natural Language :: English
Classifier: Natural Language :: Spanish
Classifier: Topic :: Software Development :: Libraries :: Python Modules
Classifier: Topic :: Text Processing :: Linguistic
Classifier: Topic :: Scientific/Engineering :: Artificial Intelligence
Requires-Dist: PyYAML
Requires-Dist: configargparse
Requires-Dist: networkx
Requires-Dist: pycorpus
Requires-Dist: pynaf
